[{"metric": "cpu_percentage_normalized", "t": 0.117793, "value": 100.3708}, {"metric": "cpu_percentage_normalized", "t": 2.045578, "value": 100.12914820592825}, {"metric": "cpu_percentage_normalized", "t": 4.134258, "value": 100.24082422728694}, {"metric": "cpu_percentage_normalized", "t": 6.057198, "value": 99.9379937694704}, {"metric": "cpu_percentage_normalized", "t": 8.08596, "value": 99.97167655323135}, {"metric": "cpu_percentage_normalized", "t": 10.114803, "value": 100.35603873789441}, {"metric": "cpu_percentage_normalized", "t": 12.138162, "value": 100.37223778400248}, {"metric": "cpu_percentage_normalized", "t": 14.166475, "value": 100.23660424469413}, {"metric": "cpu_percentage_normalized", "t": 16.102002, "value": 100.18666666666667}, {"metric": "cpu_percentage_normalized", "t": 18.125158, "value": 100.2914589190878}, {"metric": "cpu_percentage_normalized", "t": 20.15684, "value": 100.42506566604128}, {"metric": "cpu_percentage_normalized", "t": 22.182475, "value": 100.12177167810357}, {"metric": "cpu_percentage_normalized", "t": 24.106253, "value": 100.20965344989072}, {"metric": "cpu_percentage_normalized", "t": 26.135715, "value": 100.14642121684867}, {"metric": "cpu_percentage_normalized", "t": 28.159395, "value": 100.10106575257089}, {"metric": "cpu_percentage_normalized", "t": 30.187961, "value": 100.3600374882849}, {"metric": "cpu_percentage_normalized", "t": 32.212679, "value": 99.73852684144819}, {"metric": "cpu_percentage_normalized", "t": 34.135574, "value": 99.77245330012452}, {"metric": "cpu_percentage_normalized", "t": 36.160493, "value": 99.5534581772784}, {"metric": "cpu_percentage_normalized", "t": 38.186342, "value": 99.95466416744767}, {"metric": "cpu_percentage_normalized", "t": 40.208564, "value": 100.1077469616703}, {"metric": "cpu_percentage_normalized", "t": 42.234848, "value": 100.20232064878354}, {"metric": "cpu_percentage_normalized", "t": 44.258824, "value": 99.81761399125546}, {"metric": "cpu_percentage_normalized", "t": 46.191286, "value": 100.14307355242566}, {"metric": "cpu_percentage_normalized", "t": 48.224289, "value": 99.95395755305869}, {"metric": "cpu_percentage_normalized", "t": 50.248169, "value": 100.13176177112567}, {"metric": "cpu_percentage_normalized", "t": 52.276127, "value": 100.01595498593309}, {"metric": "cpu_percentage_normalized", "t": 54.201676, "value": 100.20072364316906}, {"metric": "cpu_percentage_normalized", "t": 56.224569, "value": 100.31960024984386}, {"metric": "cpu_percentage_normalized", "t": 58.250159, "value": 100.23098907956319}, {"metric": "metrics_produced_rate", "t": 0.421602, "value": 655023.1283430386}, {"metric": "metrics_produced_rate", "t": 1.437713, "value": 443849.1464023123}, {"metric": "metrics_produced_rate", "t": 2.549959, "value": 436953.6954954209}, {"metric": "metrics_produced_rate", "t": 3.526326, "value": 539756.0548441313}, {"metric": "metrics_produced_rate", "t": 4.638555, "value": 330867.114596005}, {"metric": "metrics_produced_rate", "t": 5.650785, "value": 493958.88286259054}, {"metric": "metrics_produced_rate", "t": 6.667259, "value": 368922.3728299985}, {"metric": "metrics_produced_rate", "t": 7.780215, "value": 507657.08617411647}, {"metric": "metrics_produced_rate", "t": 8.791452, "value": 561688.3084776368}, {"metric": "metrics_produced_rate", "t": 9.808717, "value": 335212.55523388693}, {"metric": "metrics_produced_rate", "t": 10.920827, "value": 443301.47197669296}, {"metric": "metrics_produced_rate", "t": 11.933048, "value": 523601.0713075504}, {"metric": "metrics_produced_rate", "t": 12.949464, "value": 432893.61836098606}, {"metric": "metrics_produced_rate", "t": 14.062112, "value": 379275.3862856896}, {"metric": "metrics_produced_rate", "t": 15.073432, "value": 399477.9100581418}, {"metric": "metrics_produced_rate", "t": 16.102002, "value": 476389.55054104247}, {"metric": "metrics_produced_rate", "t": 17.213884, "value": 446989.8784223505}, {"metric": "metrics_produced_rate", "t": 18.225917, "value": 522710.2278285392}, {"metric": "metrics_produced_rate", "t": 19.24515, "value": 380678.4121000791}, {"metric": "metrics_produced_rate", "t": 20.359137, "value": 275586.69894711516}, {"metric": "metrics_produced_rate", "t": 21.371695, "value": 238998.65489186792}, {"metric": "metrics_produced_rate", "t": 22.38576, "value": 106502.04868524207}, {"metric": "metrics_produced_rate", "t": 23.49761, "value": 206862.43647974095}, {"metric": "metrics_produced_rate", "t": 24.509305, "value": 90936.49765986783}, {"metric": "metrics_produced_rate", "t": 25.527084, "value": 237772.64022936218}, {"metric": "metrics_produced_rate", "t": 26.639331, "value": 258036.20958294335}, {"metric": "metrics_produced_rate", "t": 27.651824, "value": 263705.52685302513}, {"metric": "metrics_produced_rate", "t": 28.667557, "value": 261879.84440793004}, {"metric": "metrics_produced_rate", "t": 29.780656, "value": 236277.2763249271}, {"metric": "metrics_produced_rate", "t": 30.79202, "value": 309483.03479261673}, {"metric": "metrics_produced_rate", "t": 31.805288, "value": 218106.1673713174}, {"metric": "metrics_produced_rate", "t": 32.917566, "value": 236451.6784472946}, {"metric": "metrics_produced_rate", "t": 33.929598, "value": 305326.31379244925}, {"metric": "metrics_produced_rate", "t": 34.942909, "value": 202307.09032074062}, {"metric": "metrics_produced_rate", "t": 36.055749, "value": 304626.0019409798}, {"metric": "metrics_produced_rate", "t": 37.068068, "value": 261775.1914169348}, {"metric": "metrics_produced_rate", "t": 38.084055, "value": 259845.84448423062}, {"metric": "metrics_produced_rate", "t": 39.19588, "value": 233849.75153463898}, {"metric": "metrics_produced_rate", "t": 40.208564, "value": 306117.2093170229}, {"metric": "metrics_produced_rate", "t": 41.223731, "value": 312263.89352687786}, {"metric": "metrics_produced_rate", "t": 42.335613, "value": 220347.12316594747}, {"metric": "metrics_produced_rate", "t": 43.34851, "value": 375161.5415980105}, {"metric": "metrics_produced_rate", "t": 44.369247, "value": 298803.7075172155}, {"metric": "metrics_produced_rate", "t": 45.48229, "value": 225507.90939792985}, {"metric": "metrics_produced_rate", "t": 46.493423, "value": 347135.3422348989}, {"metric": "metrics_produced_rate", "t": 47.515258, "value": 200619.4737897997}, {"metric": "metrics_produced_rate", "t": 48.627071, "value": 301309.66268608125}, {"metric": "metrics_produced_rate", "t": 49.639348, "value": 275616.2591859738}, {"metric": "metrics_produced_rate", "t": 50.655326, "value": 196854.65630161288}, {"metric": "metrics_produced_rate", "t": 51.768553, "value": 289249.1827812297}, {"metric": "metrics_produced_rate", "t": 52.779603, "value": 255180.25814747048}, {"metric": "metrics_produced_rate", "t": 53.794627, "value": 238418.0078500607}, {"metric": "metrics_produced_rate", "t": 54.906421, "value": 335493.8055071353}, {"metric": "metrics_produced_rate", "t": 55.918374, "value": 214436.83649339442}, {"metric": "metrics_produced_rate", "t": 56.931801, "value": 304906.02677844575}, {"metric": "metrics_produced_rate", "t": 58.044409, "value": 195037.24582242803}, {"metric": "metrics_produced_rate", "t": 59.05787, "value": 279241.135080679}, {"metric": "metrics_received_rate", "t": 0.117793, "value": 84981.9081175641}, {"metric": "metrics_received_rate", "t": 1.129877, "value": 161883.79620663897}, {"metric": "metrics_received_rate", "t": 2.146434, "value": 161171.48374365628}, {"metric": "metrics_received_rate", "t": 3.117806, "value": 84334.32299880993}, {"metric": "metrics_received_rate", "t": 4.134258, "value": 171459.15399841804}, {"metric": "metrics_received_rate", "t": 5.146653, "value": 161834.06674272395}, {"metric": "metrics_received_rate", "t": 6.158057, "value": 89451.89063915113}, {"metric": "metrics_received_rate", "t": 7.175516, "value": 161028.6016438992}, {"metric": "metrics_received_rate", "t": 8.186691, "value": 89116.12727767201}, {"metric": "metrics_received_rate", "t": 9.198901, "value": 161152.3300500884}, {"metric": "metrics_received_rate", "t": 10.215595, "value": 99727.15487649184}, {"metric": "metrics_received_rate", "t": 11.227611, "value": 169989.4072820983}, {"metric": "metrics_received_rate", "t": 12.238977, "value": 170098.65864583149}, {"metric": "metrics_received_rate", "t": 13.256279, "value": 88579.39923444563}, {"metric": "metrics_received_rate", "t": 14.267365, "value": 155824.5292685291}, {"metric": "metrics_received_rate", "t": 15.279269, "value": 161912.59249889318}, {"metric": "metrics_received_rate", "t": 16.205208, "value": 181567.03627344783}, {"metric": "metrics_received_rate", "t": 17.213884, "value": 162430.7508060071}, {"metric": "metrics_received_rate", "t": 18.225917, "value": 178081.1495277328}, {"metric": "metrics_received_rate", "t": 19.348636, "value": 195895.856398618}, {"metric": "metrics_received_rate", "t": 20.359137, "value": 97282.43712772179}, {"metric": "metrics_received_rate", "t": 21.371695, "value": 163680.50027751495}, {"metric": "metrics_received_rate", "t": 22.488809, "value": 153996.81679756945}, {"metric": "metrics_received_rate", "t": 23.49761, "value": 246407.3687476519}, {"metric": "metrics_received_rate", "t": 24.509305, "value": 161946.04104992116}, {"metric": "metrics_received_rate", "t": 25.63028, "value": 226545.64107138873}, {"metric": "metrics_received_rate", "t": 26.639331, "value": 333541.1193289537}, {"metric": "metrics_received_rate", "t": 27.651824, "value": 250818.5241774511}, {"metric": "metrics_received_rate", "t": 28.771487, "value": 236549.74755797055}, {"metric": "metrics_received_rate", "t": 29.780656, "value": 264344.22777552623}, {"metric": "metrics_received_rate", "t": 30.79202, "value": 264838.37668732525}, {"metric": "metrics_received_rate", "t": 31.908035, "value": 227552.49705425106}, {"metric": "metrics_received_rate", "t": 32.917566, "value": 267189.4176602799}, {"metric": "metrics_received_rate", "t": 33.929598, "value": 259114.33630557134}, {"metric": "metrics_received_rate", "t": 35.045215, "value": 220290.65530553943}, {"metric": "metrics_received_rate", "t": 36.055749, "value": 259086.7798609448}, {"metric": "metrics_received_rate", "t": 37.068068, "value": 238675.75339394005}, {"metric": "metrics_received_rate", "t": 38.186342, "value": 224073.88529108252}, {"metric": "metrics_received_rate", "t": 39.19588, "value": 329624.04585067625}, {"metric": "metrics_received_rate", "t": 40.208564, "value": 261151.55369295852}, {"metric": "metrics_received_rate", "t": 41.326101, "value": 234572.99400377795}, {"metric": "metrics_received_rate", "t": 42.335613, "value": 254665.620616694}, {"metric": "metrics_received_rate", "t": 43.34851, "value": 243704.9374220676}, {"metric": "metrics_received_rate", "t": 44.472699, "value": 225897.9584393727}, {"metric": "metrics_received_rate", "t": 45.48229, "value": 324567.0771629304}, {"metric": "metrics_received_rate", "t": 46.493423, "value": 512581.43092946225}, {"metric": "metrics_received_rate", "t": 47.618293, "value": 219239.55657098154}, {"metric": "metrics_received_rate", "t": 48.627071, "value": 251742.20690776367}, {"metric": "metrics_received_rate", "t": 49.639348, "value": 258964.69049479536}, {"metric": "metrics_received_rate", "t": 50.759487, "value": 226714.72022668616}, {"metric": "metrics_received_rate", "t": 51.768553, "value": 328549.3713988976}, {"metric": "metrics_received_rate", "t": 52.779603, "value": 178911.0330844172}, {"metric": "metrics_received_rate", "t": 53.897195, "value": 250710.45605194027}, {"metric": "metrics_received_rate", "t": 54.906421, "value": 285058.05439019605}, {"metric": "metrics_received_rate", "t": 55.918374, "value": 229528.4464792337}, {"metric": "metrics_received_rate", "t": 57.034056, "value": 293703.76146608085}, {"metric": "metrics_received_rate", "t": 58.044409, "value": 178377.26022489168}, {"metric": "metrics_received_rate", "t": 59.05787, "value": 258662.14881480395}, {"metric": "network_rx_bytes_rate", "t": 0.117793, "value": 19974148.449227385}, {"metric": "network_rx_bytes_rate", "t": 2.045578, "value": 22298787.46851957}, {"metric": "network_rx_bytes_rate", "t": 4.134258, "value": 20699103.740161248}, {"metric": "network_rx_bytes_rate", "t": 6.057198, "value": 21030889.159308143}, {"metric": "network_rx_bytes_rate", "t": 8.08596, "value": 21583230.561297975}, {"metric": "network_rx_bytes_rate", "t": 10.114803, "value": 19164691.402932607}, {"metric": "network_rx_bytes_rate", "t": 12.138162, "value": 20616557.911868334}, {"metric": "network_rx_bytes_rate", "t": 14.166475, "value": 19011550.97857185}, {"metric": "network_rx_bytes_rate", "t": 16.102002, "value": 20430927.597496703}, {"metric": "network_rx_bytes_rate", "t": 18.125158, "value": 16681177.328886155}, {"metric": "network_rx_bytes_rate", "t": 20.15684, "value": 20829786.354360573}, {"metric": "network_rx_bytes_rate", "t": 22.182475, "value": 21328316.799423393}, {"metric": "network_rx_bytes_rate", "t": 24.106253, "value": 18413656.357438333}, {"metric": "network_rx_bytes_rate", "t": 26.135715, "value": 11621587.88880994}, {"metric": "network_rx_bytes_rate", "t": 28.159395, "value": 12231427.399588866}, {"metric": "network_rx_bytes_rate", "t": 30.187961, "value": 12136591.562709816}, {"metric": "network_rx_bytes_rate", "t": 32.212679, "value": 11340977.360797899}, {"metric": "network_rx_bytes_rate", "t": 34.135574, "value": 11961576.165105218}, {"metric": "network_rx_bytes_rate", "t": 36.160493, "value": 11483432.670640158}, {"metric": "network_rx_bytes_rate", "t": 38.186342, "value": 12358840.170219991}, {"metric": "network_rx_bytes_rate", "t": 40.208564, "value": 11508689.451504335}, {"metric": "network_rx_bytes_rate", "t": 42.234848, "value": 11198856.62621824}, {"metric": "network_rx_bytes_rate", "t": 44.258824, "value": 12732741.89022004}, {"metric": "network_rx_bytes_rate", "t": 46.191286, "value": 11790390.186197711}, {"metric": "network_rx_bytes_rate", "t": 48.224289, "value": 11148623.9813714}, {"metric": "network_rx_bytes_rate", "t": 50.248169, "value": 11369003.102950767}, {"metric": "network_rx_bytes_rate", "t": 52.276127, "value": 12884194.84032707}, {"metric": "network_rx_bytes_rate", "t": 54.201676, "value": 12925128.885320498}, {"metric": "network_rx_bytes_rate", "t": 56.224569, "value": 12125468.821138835}, {"metric": "network_rx_bytes_rate", "t": 58.250159, "value": 11361769.16355235}, {"metric": "network_tx_bytes_rate", "t": 0.117793, "value": 5544837.700671184}, {"metric": "network_tx_bytes_rate", "t": 2.045578, "value": 6662629.90945567}, {"metric": "network_tx_bytes_rate", "t": 4.134258, "value": 6034634.314495279}, {"metric": "network_tx_bytes_rate", "t": 6.057198, "value": 5766814.357182231}, {"metric": "network_tx_bytes_rate", "t": 8.08596, "value": 5623145.543932704}, {"metric": "network_tx_bytes_rate", "t": 10.114803, "value": 5695000.549574314}, {"metric": "network_tx_bytes_rate", "t": 12.138162, "value": 7226448.198268325}, {"metric": "network_tx_bytes_rate", "t": 14.166475, "value": 6896269.461370114}, {"metric": "network_tx_bytes_rate", "t": 16.102002, "value": 5813417.224352851}, {"metric": "network_tx_bytes_rate", "t": 18.125158, "value": 8723542.326938704}, {"metric": "network_tx_bytes_rate", "t": 20.15684, "value": 5480531.402059968}, {"metric": "network_tx_bytes_rate", "t": 22.182475, "value": 7303098.534533616}, {"metric": "network_tx_bytes_rate", "t": 24.106253, "value": 5551374.430937458}, {"metric": "network_tx_bytes_rate", "t": 26.135715, "value": 11704859.218847161}, {"metric": "network_tx_bytes_rate", "t": 28.159395, "value": 11882749.248893104}, {"metric": "network_tx_bytes_rate", "t": 30.187961, "value": 11567535.39199612}, {"metric": "network_tx_bytes_rate", "t": 32.212679, "value": 10971640.495120801}, {"metric": "network_tx_bytes_rate", "t": 34.135574, "value": 11622409.439933017}, {"metric": "network_tx_bytes_rate", "t": 36.160493, "value": 10755637.632912723}, {"metric": "network_tx_bytes_rate", "t": 38.186342, "value": 12467528.9224419}, {"metric": "network_tx_bytes_rate", "t": 40.208564, "value": 11101806.329868827}, {"metric": "network_tx_bytes_rate", "t": 42.234848, "value": 10918617.528441226}, {"metric": "network_tx_bytes_rate", "t": 44.258824, "value": 12461006.948698996}, {"metric": "network_tx_bytes_rate", "t": 46.191286, "value": 11246416.229659367}, {"metric": "network_tx_bytes_rate", "t": 48.224289, "value": 10837645.099392377}, {"metric": "network_tx_bytes_rate", "t": 50.248169, "value": 11213782.931794375}, {"metric": "network_tx_bytes_rate", "t": 52.276127, "value": 12687167.091231672}, {"metric": "network_tx_bytes_rate", "t": 54.201676, "value": 10935966.83335506}, {"metric": "network_tx_bytes_rate", "t": 56.224569, "value": 11987073.463598916}, {"metric": "network_tx_bytes_rate", "t": 58.250159, "value": 11204074.862138934}, {"metric": "ram_mib", "t": 0.117793, "value": 2412.80859375}, {"metric": "ram_mib", "t": 2.045578, "value": 3128.3046875}, {"metric": "ram_mib", "t": 4.134258, "value": 3847.328125}, {"metric": "ram_mib", "t": 6.057198, "value": 4478.6015625}, {"metric": "ram_mib", "t": 8.08596, "value": 5175.24609375}, {"metric": "ram_mib", "t": 10.114803, "value": 5826.97265625}, {"metric": "ram_mib", "t": 12.138162, "value": 6487.109375}, {"metric": "ram_mib", "t": 14.166475, "value": 7041.7578125}, {"metric": "ram_mib", "t": 16.102002, "value": 7663.65234375}, {"metric": "ram_mib", "t": 18.125158, "value": 8039.4375}, {"metric": "ram_mib", "t": 20.15684, "value": 8789.0859375}, {"metric": "ram_mib", "t": 22.182475, "value": 9379.67578125}, {"metric": "ram_mib", "t": 24.106253, "value": 10054.25390625}, {"metric": "ram_mib", "t": 26.135715, "value": 10149.4609375}, {"metric": "ram_mib", "t": 28.159395, "value": 10186.984375}, {"metric": "ram_mib", "t": 30.187961, "value": 10190.94140625}, {"metric": "ram_mib", "t": 32.212679, "value": 10192.99609375}, {"metric": "ram_mib", "t": 34.135574, "value": 10220.51953125}, {"metric": "ram_mib", "t": 36.160493, "value": 10225.8984375}, {"metric": "ram_mib", "t": 38.186342, "value": 10227.46875}, {"metric": "ram_mib", "t": 40.208564, "value": 10227.73046875}, {"metric": "ram_mib", "t": 42.234848, "value": 10237.65625}, {"metric": "ram_mib", "t": 44.258824, "value": 10233.046875}, {"metric": "ram_mib", "t": 46.191286, "value": 10241.80859375}, {"metric": "ram_mib", "t": 48.224289, "value": 10261.08203125}, {"metric": "ram_mib", "t": 50.248169, "value": 10262.00390625}, {"metric": "ram_mib", "t": 52.276127, "value": 10274.06640625}, {"metric": "ram_mib", "t": 54.201676, "value": 10282.4375}, {"metric": "ram_mib", "t": 56.224569, "value": 10337.34765625}, {"metric": "ram_mib", "t": 58.250159, "value": 10349.84375}]