[{"metric": "cpu_percentage_normalized", "t": 0.034865, "value": 44.97360850531582}, {"metric": "cpu_percentage_normalized", "t": 2.048026, "value": 44.93966186599875}, {"metric": "cpu_percentage_normalized", "t": 4.062022, "value": 45.07024664377147}, {"metric": "cpu_percentage_normalized", "t": 6.075416, "value": 47.63009082367679}, {"metric": "cpu_percentage_normalized", "t": 8.096384, "value": 48.92547051442911}, {"metric": "cpu_percentage_normalized", "t": 10.113396, "value": 48.6334123518403}, {"metric": "cpu_percentage_normalized", "t": 12.12896, "value": 48.21784037558686}, {"metric": "cpu_percentage_normalized", "t": 14.143363, "value": 49.183859208045256}, {"metric": "cpu_percentage_normalized", "t": 16.157256, "value": 48.599837245696406}, {"metric": "cpu_percentage_normalized", "t": 18.173053, "value": 48.73926897844424}, {"metric": "logs_produced_rate", "t": 0.336659, "value": 385599.03291762545}, {"metric": "logs_produced_rate", "t": 1.443473, "value": 361397.6693464304}, {"metric": "logs_produced_rate", "t": 2.449798, "value": 397485.9016719251}, {"metric": "logs_produced_rate", "t": 3.457048, "value": 397120.8736659221}, {"metric": "logs_produced_rate", "t": 4.564724, "value": 361116.42754740553}, {"metric": "logs_produced_rate", "t": 5.570982, "value": 397544.1685929453}, {"metric": "logs_produced_rate", "t": 6.579039, "value": 396675.9816161189}, {"metric": "logs_produced_rate", "t": 7.591817, "value": 394984.88316294394}, {"metric": "logs_produced_rate", "t": 8.698852, "value": 361209.89851269376}, {"metric": "logs_produced_rate", "t": 9.709155, "value": 395920.8277120824}, {"metric": "logs_produced_rate", "t": 10.717554, "value": 396668.38225741993}, {"metric": "logs_produced_rate", "t": 11.825093, "value": 361161.0968101349}, {"metric": "logs_produced_rate", "t": 12.831738, "value": 397359.5458180391}, {"metric": "logs_produced_rate", "t": 13.839111, "value": 397072.38530315977}, {"metric": "logs_produced_rate", "t": 14.94643, "value": 361377.34473986266}, {"metric": "logs_produced_rate", "t": 15.953651, "value": 397068.76643755444}, {"metric": "logs_produced_rate", "t": 16.962044, "value": 396607.275139752}, {"metric": "logs_produced_rate", "t": 18.0698, "value": 361119.23564395047}, {"metric": "logs_produced_rate", "t": 19.076418, "value": 397306.62475735584}, {"metric": "logs_received_rate", "t": 0.135273, "value": 384738.9450073389}, {"metric": "logs_received_rate", "t": 1.142054, "value": 397369.43784199347}, {"metric": "logs_received_rate", "t": 2.148456, "value": 397455.48995331884}, {"metric": "logs_received_rate", "t": 3.154723, "value": 397445.2108635183}, {"metric": "logs_received_rate", "t": 4.16243, "value": 396877.26690397115}, {"metric": "logs_received_rate", "t": 5.169327, "value": 397323.6587257684}, {"metric": "logs_received_rate", "t": 6.175845, "value": 397314.3053576786}, {"metric": "logs_received_rate", "t": 7.184942, "value": 396457.426788505}, {"metric": "logs_received_rate", "t": 8.196832, "value": 395205.0124025339}, {"metric": "logs_received_rate", "t": 9.203969, "value": 397228.97679263103}, {"metric": "logs_received_rate", "t": 10.213902, "value": 396002.50709700544}, {"metric": "logs_received_rate", "t": 11.222782, "value": 396479.26413448574}, {"metric": "logs_received_rate", "t": 12.229393, "value": 397309.38763832307}, {"metric": "logs_received_rate", "t": 13.236658, "value": 397178.4982105007}, {"metric": "logs_received_rate", "t": 14.243777, "value": 397236.0763723055}, {"metric": "logs_received_rate", "t": 15.250996, "value": 397037.7842356031}, {"metric": "logs_received_rate", "t": 16.257674, "value": 397219.369053461}, {"metric": "logs_received_rate", "t": 17.266868, "value": 396355.90382027643}, {"metric": "logs_received_rate", "t": 18.273457, "value": 397477.0238895915}, {"metric": "logs_received_rate", "t": 19.279984, "value": 397406.1301882612}, {"metric": "network_rx_bytes_rate", "t": 0.034865, "value": 90857167.82408002}, {"metric": "network_rx_bytes_rate", "t": 2.048026, "value": 87690452.97420324}, {"metric": "network_rx_bytes_rate", "t": 4.062022, "value": 87759936.9611459}, {"metric": "network_rx_bytes_rate", "t": 6.075416, "value": 87662440.13839318}, {"metric": "network_rx_bytes_rate", "t": 8.096384, "value": 87499044.02246845}, {"metric": "network_rx_bytes_rate", "t": 10.113396, "value": 87608990.42742434}, {"metric": "network_rx_bytes_rate", "t": 12.12896, "value": 87638772.07570685}, {"metric": "network_rx_bytes_rate", "t": 14.143363, "value": 87711151.64145406}, {"metric": "network_rx_bytes_rate", "t": 16.157256, "value": 87655816.37157486}, {"metric": "network_rx_bytes_rate", "t": 18.173053, "value": 87676844.94023952}, {"metric": "network_tx_bytes_rate", "t": 0.034865, "value": 90994027.54146898}, {"metric": "network_tx_bytes_rate", "t": 2.048026, "value": 87843222.673199}, {"metric": "network_tx_bytes_rate", "t": 4.062022, "value": 87889584.68636481}, {"metric": "network_tx_bytes_rate", "t": 6.075416, "value": 87824748.6582358}, {"metric": "network_tx_bytes_rate", "t": 8.096384, "value": 87622797.09525336}, {"metric": "network_tx_bytes_rate", "t": 10.113396, "value": 87738079.89243495}, {"metric": "network_tx_bytes_rate", "t": 12.12896, "value": 87791280.25703973}, {"metric": "network_tx_bytes_rate", "t": 14.143363, "value": 87855129.28644367}, {"metric": "network_tx_bytes_rate", "t": 16.157256, "value": 87800513.73136507}, {"metric": "network_tx_bytes_rate", "t": 18.173053, "value": 87840581.16963166}, {"metric": "ram_mib", "t": 0.034865, "value": 50.6796875}, {"metric": "ram_mib", "t": 2.048026, "value": 50.51953125}, {"metric": "ram_mib", "t": 4.062022, "value": 51.00390625}, {"metric": "ram_mib", "t": 6.075416, "value": 50.66796875}, {"metric": "ram_mib", "t": 8.096384, "value": 50.94921875}, {"metric": "ram_mib", "t": 10.113396, "value": 50.6328125}, {"metric": "ram_mib", "t": 12.12896, "value": 50.703125}, {"metric": "ram_mib", "t": 14.143363, "value": 51.21875}, {"metric": "ram_mib", "t": 16.157256, "value": 50.9765625}, {"metric": "ram_mib", "t": 18.173053, "value": 50.74609375}]